crowcommand/__init__.py
crowcommand/client.py
crowcommand/internal_logger.py
crowcommand/logger.py
crowcommand-0.1.4.dist-info/AUTHORS.rst
crowcommand-0.1.4.dist-info/LICENSE
crowcommand-0.1.4.dist-info/METADATA
crowcommand-0.1.4.dist-info/WHEEL
crowcommand-0.1.4.dist-info/top_level.txt
crowcommand-0.1.4.dist-info/RECORD
